<annotation>
    <folder>additional_dataset</folder>
    <filename>ubp7.jpeg</filename>
    <size>
        <width>177</width>
        <height>284</height>
        <depth>3</depth>
    </size>
    <object>
        <name>height_frame</name>
        <pose>Unspecified</pose>
        <truncated>0</truncated>
        <occluded>0</occluded>
        <difficult>0</difficult>
        <bndbox>
            <xmin>17.903954</xmin>
            <ymin>11.961272</ymin>
            <xmax>130.265533</xmax>
            <ymax>267.059845</ymax>
        </bndbox>
    </object>
    <object>
        <name>hip_frame</name>
        <pose>Unspecified</pose>
        <truncated>0</truncated>
        <occluded>0</occluded>
        <difficult>0</difficult>
        <bndbox>
            <xmin>35.802258</xmin>
            <ymin>223.214783</ymin>
            <xmax>110.378525</xmax>
            <ymax>233.179565</ymax>
        </bndbox>
    </object>
    <object>
        <name>waist_frame</name>
        <pose>Unspecified</pose>
        <truncated>0</truncated>
        <occluded>0</occluded>
        <difficult>0</difficult>
        <bndbox>
            <xmin>42.762711</xmin>
            <ymin>168.408447</ymin>
            <xmax>106.401131</xmax>
            <ymax>176.380280</ymax>
        </bndbox>
    </object>
    <object>
        <name>shoulder_frame</name>
        <pose>Unspecified</pose>
        <truncated>0</truncated>
        <occluded>0</occluded>
        <difficult>0</difficult>
        <bndbox>
            <xmin>39.779663</xmin>
            <ymin>90.683090</ymin>
            <xmax>120.322037</xmax>
            <ymax>99.651413</ymax>
        </bndbox>
    </object>
</annotation>