<annotation>
    <folder>opencv-dataset</folder>
    <filename>WIN_20231021_19_00_44_Pro.jpg</filename>
    <size>
        <width>1280</width>
        <height>720</height>
        <depth>3</depth>
    </size>
    <object>
        <name>height_frame</name>
        <pose>Unspecified</pose>
        <truncated>0</truncated>
        <occluded>0</occluded>
        <difficult>0</difficult>
        <bndbox>
            <xmin>603.528870</xmin>
            <ymin>135.812500</ymin>
            <xmax>905.292969</xmax>
            <ymax>720.000000</ymax>
        </bndbox>
    </object>
    <object>
        <name>hip_frame</name>
        <pose>Unspecified</pose>
        <truncated>0</truncated>
        <occluded>0</occluded>
        <difficult>0</difficult>
        <bndbox>
            <xmin>653.489868</xmin>
            <ymin>526.269470</ymin>
            <xmax>869.321106</xmax>
            <ymax>555.229187</ymax>
        </bndbox>
    </object>
    <object>
        <name>waist_frame</name>
        <pose>Unspecified</pose>
        <truncated>0</truncated>
        <occluded>0</occluded>
        <difficult>0</difficult>
        <bndbox>
            <xmin>646.495300</xmin>
            <ymin>427.406952</ymin>
            <xmax>867.322632</xmax>
            <ymax>459.362518</ymax>
        </bndbox>
    </object>
    <object>
        <name>shoulder_frame</name>
        <pose>Unspecified</pose>
        <truncated>0</truncated>
        <occluded>0</occluded>
        <difficult>0</difficult>
        <bndbox>
            <xmin>633.505432</xmin>
            <ymin>242.663895</ymin>
            <xmax>857.330444</xmax>
            <ymax>271.623627</ymax>
        </bndbox>
    </object>
</annotation>